erlc_api/__init__.py
erlc_api/client.py
erlc_api/discord_tools.py
erlc_api/errors.py
erlc_api/events.py
erlc_api/models.py
erlc_api/presence.py
erlc_api/scheduler.py
erlc_api/session.py
erlc_api/utils.py
erlc_api/verification.py
svapihelper_lc-1.0.0.dist-info/METADATA
svapihelper_lc-1.0.0.dist-info/WHEEL
svapihelper_lc-1.0.0.dist-info/top_level.txt
svapihelper_lc-1.0.0.dist-info/RECORD
