Metadata-Version: 2.4
Name: svapihelper-lc
Version: 1.0.0
Summary: ERLC API Wrapper for Discord Bots
Home-page: https://github.com/ctdevs/SVAPIHELPER-LC
Author: CT Devs
License: MIT
Requires-Python: >=3.9
Requires-Dist: aiohttp
Requires-Dist: discord.py
